jxes/__init__.py
jxes/jxes.py
jxes-0.1.dist-info/METADATA
jxes-0.1.dist-info/WHEEL
jxes-0.1.dist-info/licenses/LICENSE
jxes-0.1.dist-info/RECORD
