Metadata-Version: 2.3
Name: jxes
Version: 0.1
Summary: Python implementation of JXES
Project-URL: Homepage, https://github.com/MaxVidgof/python-jxes
Project-URL: Issues, https://github.com/MaxVidgof/python-jxes/issues
Author-email: Maxim Vidgof <maxim.vidgof@wu.ac.at>
License-File: LICENSE
Classifier: License :: OSI Approved :: Apache Software License
Classifier: Operating System :: OS Independent
Classifier: Programming Language :: Python :: 3
Requires-Python: >=3.10
Requires-Dist: pm4py
